{
    "id": 987746,
    "authors": [
        {
            "id": 14177054,
            "name": "Thomas Spellman",
            "url": "https://addons.thunderbird.net/en-US/thunderbird/user/thosmos/",
            "username": "thosmos",
            "picture_url": null
        }
    ],
    "average_daily_users": 743,
    "categories": {
        "thunderbird": [
            "composition"
        ]
    },
    "contributions_url": "https://paypal.me/thosmos",
    "current_version": {
        "id": 2473383,
        "compatibility": {
            "thunderbird": {
                "max": "*",
                "min": "68.0"
            }
        },
        "edit_url": "https://addons.thunderbird.net/en-US/developers/addon/filelink-provider-for-owncloud/versions/2473383",
        "files": [
            {
                "id": 1016505,
                "created": "2020-02-04T06:50:58Z",
                "hash": "sha256:979f9a4f8981ad41a5dc0819d72b6ad873ba1a5eb3a4d630f9975fb978587ec6",
                "is_restart_required": false,
                "is_webextension": true,
                "is_mozilla_signed_extension": false,
                "platform": "all",
                "size": 48788,
                "status": "public",
                "url": "https://addons.thunderbird.net/thunderbird/downloads/file/1016505/filelink_provider_for_owncloud_and_nextcloud-1.8-tb.xpi?src=",
                "permissions": [
                    "<all_urls>",
                    "storage"
                ]
            }
        ],
        "is_strict_compatibility_enabled": false,
        "license": {
            "id": 3338,
            "name": {
                "en-US": "Mozilla Public License, version 2.0"
            },
            "url": "http://www.mozilla.org/MPL/2.0/"
        },
        "release_notes": {
            "en-US": "French language"
        },
        "reviewed": null,
        "url": "https://addons.thunderbird.net/en-US/thunderbird/addon/filelink-provider-for-owncloud/versions/1.8",
        "version": "1.8"
    },
    "default_locale": "en-US",
    "description": {
        "en-US": "This requires your OwnCloud server to have public link sharing enabled and optionally to have the OAuth2 plugin enabled for creating an app authentication token.\n\nNextCloud should work with the default settings\n\nThis extension requires 4 pieces of data: \n<ol><li>your WebDAV URL, which you can get from your personal Settings after you log in to your cloud service</li><li>your username</li><li>your password OR an app token you generate</li><li>the path where you want your attachments saved to.</li></ol>\nThere is a known issue with Thunderbird itself where if you save an email draft and then re-open it, you will be unable to delete the attachment."
    },
    "developer_comments": null,
    "edit_url": "https://addons.thunderbird.net/en-US/developers/addon/filelink-provider-for-owncloud/edit",
    "guid": "filelink-owncloud@thosmos.com",
    "has_eula": false,
    "has_privacy_policy": false,
    "homepage": null,
    "icon_url": "https://addons.thunderbird.net/user-media/addon_icons/987/987746-64.png?modified=4112086b",
    "icons": {
        "32": "https://addons.thunderbird.net/user-media/addon_icons/987/987746-32.png?modified=4112086b",
        "64": "https://addons.thunderbird.net/user-media/addon_icons/987/987746-64.png?modified=4112086b"
    },
    "is_disabled": false,
    "is_experimental": false,
    "is_featured": false,
    "is_source_public": true,
    "last_updated": "2020-02-04T06:55:03Z",
    "name": {
        "en-US": "FileLink Provider for OwnCloud and NextCloud"
    },
    "previews": [],
    "public_stats": true,
    "ratings": {
        "bayesian_average": 4.52045,
        "count": 7,
        "average": 4.7143,
        "text_count": 7
    },
    "ratings_url": "https://addons.thunderbird.net/en-US/thunderbird/addon/filelink-provider-for-owncloud/reviews/",
    "requires_payment": false,
    "review_url": "https://addons.thunderbird.net/en-US/reviewers/review/987746",
    "slug": "filelink-provider-for-owncloud",
    "status": "public",
    "summary": {
        "en-US": "Uploads your large attachments to your OwnCloud or NextCloud server and instead inserts a public link into your email."
    },
    "support_email": null,
    "support_url": {
        "en-US": "https://github.com/thosmos/filelink-owncloud"
    },
    "tags": [
        "firefox57",
        "thunderbird68"
    ],
    "type": "extension",
    "url": "https://addons.thunderbird.net/en-US/thunderbird/addon/filelink-provider-for-owncloud/",
    "weekly_downloads": 0,
    "xpilib": {
        "ext_comp": {
            "compNoMax": true,
            "mext": true,
            "comp68": true
        }
    }
}