{
    "id": 410950,
    "authors": [
        {
            "id": 6739994,
            "name": "Mirsad Čirkić",
            "url": "https://addons.thunderbird.net/en-US/thunderbird/user/mirsadcirkic/",
            "username": "mirsadcirkic",
            "picture_url": null
        }
    ],
    "average_daily_users": 0,
    "categories": {
        "firefox": [
            "language-support"
        ],
        "seamonkey": [
            "language-support-and-translation"
        ],
        "thunderbird": [
            "language-support"
        ]
    },
    "contributions_url": null,
    "current_version": {
        "id": 1402472,
        "compatibility": {
            "firefox": {
                "max": "56.*",
                "min": "2.0b1"
            },
            "seamonkey": {
                "max": "2.16.*",
                "min": "1.1a"
            },
            "thunderbird": {
                "max": "31.*",
                "min": "2.0a1"
            }
        },
        "edit_url": "https://addons.thunderbird.net/en-US/developers/addon/bosnian-spell-checker/versions/1402472",
        "files": [
            {
                "id": 180994,
                "created": "2012-12-05T15:55:22Z",
                "hash": "sha256:3c1c3421d7d19ec2cf42cd484403fd2d3e553fe34bc879e0a520a8b4ab195d96",
                "is_restart_required": true,
                "is_webextension": false,
                "is_mozilla_signed_extension": false,
                "platform": "all",
                "size": 119214,
                "status": "public",
                "url": "https://addons.thunderbird.net/thunderbird/downloads/file/180994/bosnian_spell_checker-1.1-fx+tb+sm.xpi?src=",
                "permissions": []
            }
        ],
        "is_strict_compatibility_enabled": true,
        "license": {
            "id": 2834,
            "name": {
                "sv-SE": "Creative Commons",
                "en-US": "Creative Commons"
            },
            "url": "https://addons.thunderbird.net/en-US/thunderbird/addon/bosnian-spell-checker/license/1.1.1-signed.1-signed"
        },
        "release_notes": {
            "en-US": "Just added a proper Readme file"
        },
        "reviewed": null,
        "url": "https://addons.thunderbird.net/en-US/thunderbird/addon/bosnian-spell-checker/versions/1.1.1-signed.1-signed",
        "version": "1.1.1-signed.1-signed"
    },
    "default_locale": "en-US",
    "description": {
        "sv-SE": "It gives a profound spell checking experience and it makes good use of the different advanced inflections of the language. I hope it will be of greate use for all users that download it.",
        "en-US": "It gives a profound spell checking experience and it makes good use of the different advanced inflections of the language. I hope it will be of greate use for all users that download it."
    },
    "developer_comments": {
        "sv-SE": "This spell checker was and still is developed in parts by Samir Ribić, Vedran Ljubović,\nStudents at the Sarajevo School of Science and Technology, Kevin Scannel, and Mirsad Čirkić.",
        "en-US": "This work was developed and still is in parts by Samir Ribić, Vedran Ljubović, Students at the Sarajevo School of Science and Technology, Kevin Scannel, and Mirsad Čirkić."
    },
    "edit_url": "https://addons.thunderbird.net/en-US/developers/addon/bosnian-spell-checker/edit",
    "guid": "bs-BA@dictionaries.addons.mozilla.org",
    "has_eula": false,
    "has_privacy_policy": false,
    "homepage": null,
    "icon_url": "https://addons.thunderbird.net/static/img/addon-icons/default-64.png",
    "icons": {
        "32": "https://addons.thunderbird.net/static/img/addon-icons/default-32.png",
        "64": "https://addons.thunderbird.net/static/img/addon-icons/default-64.png"
    },
    "is_disabled": false,
    "is_experimental": true,
    "is_featured": false,
    "is_source_public": true,
    "last_updated": "2012-12-05T16:13:55Z",
    "name": {
        "sv-SE": "Bosnian spell checker",
        "en-US": "Bosnian spell checker"
    },
    "previews": [],
    "public_stats": true,
    "ratings": {
        "bayesian_average": 2.79641,
        "count": 1,
        "average": 5,
        "text_count": 1
    },
    "ratings_url": "https://addons.thunderbird.net/en-US/thunderbird/addon/bosnian-spell-checker/reviews/",
    "requires_payment": false,
    "review_url": "https://addons.thunderbird.net/en-US/reviewers/review/410950",
    "slug": "bosnian-spell-checker",
    "status": "public",
    "summary": {
        "sv-SE": "This is a comprehensive spell checker that contains roughly 300 000 words of the Bosnian language.",
        "en-US": "This is a comprehensive spell checker that contains more than 300 000 words of the Bosnian language."
    },
    "support_email": {
        "sv-SE": "mirsad.cirkic@gmail.com",
        "en-US": "mirsad.cirkic@gmail.com"
    },
    "support_url": null,
    "tags": [
        "bosnian",
        "language support",
        "spell checker"
    ],
    "type": "extension",
    "url": "https://addons.thunderbird.net/en-US/thunderbird/addon/bosnian-spell-checker/",
    "weekly_downloads": 25,
    "xpilib": {
        "ext_comp": {
            "mext": false,
            "compOther": true
        }
    }
}