[
    {
        "id": 2473939,
        "channel": "listed",
        "compatibility": {
            "thunderbird": {
                "max": "*",
                "min": "71.0"
            }
        },
        "edit_url": "https://addons.thunderbird.net/en-US/developers/addon/framewhite/versions/2473939",
        "files": [
            {
                "id": 1017101,
                "created": "2020-07-17T19:41:20Z",
                "hash": "sha256:b77e524110257bfa3c4d5d1c4952dd5d5b74b0872d8c8ba3adc866bca29e965d",
                "is_restart_required": false,
                "is_webextension": true,
                "is_mozilla_signed_extension": false,
                "platform": "all",
                "size": 6344,
                "status": "public",
                "url": "https://addons.thunderbird.net/thunderbird/downloads/file/1017101/framewhite-60.3-tb.xpi?src=",
                "permissions": [
                    "*://*.mozilla.org/*"
                ]
            }
        ],
        "is_strict_compatibility_enabled": false,
        "license": {
            "id": 3338,
            "name": {
                "en-US": "Mozilla Public License, version 2.0"
            },
            "text": {
                "en-US": "This Source Code Form is subject to the terms of the Mozilla Public License, v. 2.0. If a copy of the MPL was not distributed with this file, You can obtain one at <a rel=\"nofollow\" href=\"https://outgoing.prod.mozaws.net/v1/cfa1520767b4bc45590e23d48de7bec652c237ee0ad206608dfa16f2a0e21c8d/http%3A//mozilla.org/MPL/2.0/\">http://mozilla.org/MPL/2.0/</a>."
            },
            "url": "http://www.mozilla.org/MPL/2.0/"
        },
        "release_notes": {
            "en-US": "Permissions not needed were deleted, all."
        },
        "reviewed": null,
        "url": "https://addons.thunderbird.net/en-US/thunderbird/addon/framewhite/versions/60.3",
        "version": "60.3"
    },
    {
        "id": 2473442,
        "channel": "listed",
        "compatibility": {
            "thunderbird": {
                "max": "*",
                "min": "71.0"
            }
        },
        "edit_url": "https://addons.thunderbird.net/en-US/developers/addon/framewhite/versions/2473442",
        "files": [
            {
                "id": 1016570,
                "created": "2020-02-15T07:53:42Z",
                "hash": "sha256:626d169f98d30e71a441ddc7ce473960dc74f5c46d00ae5b56b8190255ead3c7",
                "is_restart_required": false,
                "is_webextension": true,
                "is_mozilla_signed_extension": false,
                "platform": "all",
                "size": 5833,
                "status": "public",
                "url": "https://addons.thunderbird.net/thunderbird/downloads/file/1016570/framewhite-59.8-tb.xpi?src=",
                "permissions": [
                    "webRequest",
                    "webNavigation",
                    "tabs",
                    "nativeMessaging",
                    "activeTab",
                    "tabHide",
                    "*://developer.mozilla.org/*",
                    "<all_urls>",
                    "https://www.thunderbird.net/*",
                    "https://start.thunderbird.net/*",
                    "*://*.mozilla.org/*"
                ]
            }
        ],
        "is_strict_compatibility_enabled": false,
        "license": {
            "id": 3338,
            "name": {
                "en-US": "Mozilla Public License, version 2.0"
            },
            "text": {
                "en-US": "This Source Code Form is subject to the terms of the Mozilla Public License, v. 2.0. If a copy of the MPL was not distributed with this file, You can obtain one at <a rel=\"nofollow\" href=\"https://outgoing.prod.mozaws.net/v1/cfa1520767b4bc45590e23d48de7bec652c237ee0ad206608dfa16f2a0e21c8d/http%3A//mozilla.org/MPL/2.0/\">http://mozilla.org/MPL/2.0/</a>."
            },
            "url": "http://www.mozilla.org/MPL/2.0/"
        },
        "release_notes": {
            "en-US": "README version 1.6\n\nTitle: FrameWhite.\nMain source: manifest.json, chrome.manifest, overlay.xul, white.css.\nDescription: \nThis is a theme with white frames.\nSo it is most white. \nAs result of test, white is fascinating without eye fatigue. \n\n\nFrom Sungho Hwang.\n\nDecember 15 2019."
        },
        "reviewed": null,
        "url": "https://addons.thunderbird.net/en-US/thunderbird/addon/framewhite/versions/59.8",
        "version": "59.8"
    },
    {
        "id": 2472039,
        "channel": "listed",
        "compatibility": {
            "thunderbird": {
                "max": "60.*",
                "min": "1.5"
            }
        },
        "edit_url": "https://addons.thunderbird.net/en-US/developers/addon/framewhite/versions/2472039",
        "files": [
            {
                "id": 1015107,
                "created": "2019-08-13T11:43:42Z",
                "hash": "sha256:6209ea5a55e05b0390b657c29c20add6bb3da58b3ae82e738823e2011678f6f6",
                "is_restart_required": true,
                "is_webextension": false,
                "is_mozilla_signed_extension": false,
                "platform": "all",
                "size": 16912,
                "status": "public",
                "url": "https://addons.thunderbird.net/thunderbird/downloads/file/1015107/framewhite-57.8-tb.xpi?src=",
                "permissions": []
            }
        ],
        "is_strict_compatibility_enabled": true,
        "license": {
            "id": 3338,
            "name": {
                "en-US": "Mozilla Public License, version 2.0"
            },
            "text": {
                "en-US": "This Source Code Form is subject to the terms of the Mozilla Public License, v. 2.0. If a copy of the MPL was not distributed with this file, You can obtain one at <a rel=\"nofollow\" href=\"https://outgoing.prod.mozaws.net/v1/cfa1520767b4bc45590e23d48de7bec652c237ee0ad206608dfa16f2a0e21c8d/http%3A//mozilla.org/MPL/2.0/\">http://mozilla.org/MPL/2.0/</a>."
            },
            "url": "http://www.mozilla.org/MPL/2.0/"
        },
        "release_notes": {
            "en-US": "I would delete !important in white.css.\n\nREADME version 1.5\n\nTitle: FrameWhite.\nMain source: install.rdf, chrome.manifest, overlay.xul, white.css.\nDescription: \nThis is a theme with white frames from default theme. \nSo it is most white. \nAs result of test, white is fascinating without eye fatigue. \nAlso, a button Switch White is changeable with default theme. \n\n\nFrom Sungho Hwang.\n\nJune 19 2019."
        },
        "reviewed": "2019-08-20T12:19:56Z",
        "url": "https://addons.thunderbird.net/en-US/thunderbird/addon/framewhite/versions/57.8",
        "version": "57.8"
    }
]