{
    "id": 986685,
    "authors": [
        {
            "id": 165138,
            "name": "Dillinger",
            "url": "https://addons.thunderbird.net/en-US/thunderbird/user/dillinger/",
            "username": "dillinger",
            "picture_url": null
        }
    ],
    "average_daily_users": 10389,
    "categories": {
        "thunderbird": [
            "appearance"
        ]
    },
    "contributions_url": "",
    "created": "2019-07-12T01:56:00Z",
    "current_version": {
        "id": 2474796,
        "compatibility": {
            "thunderbird": {
                "max": "*",
                "min": "78.0"
            }
        },
        "edit_url": "https://addons.thunderbird.net/en-US/developers/addon/phoenity-icons/versions/2474796",
        "files": [
            {
                "id": 1017958,
                "created": "2020-11-21T04:50:56Z",
                "hash": "sha256:a042d570c60f7bc23487131714b230662c705c4e087af8e58dfbec10679a6c54",
                "is_restart_required": false,
                "is_webextension": true,
                "is_mozilla_signed_extension": false,
                "platform": "all",
                "size": 382817,
                "status": "public",
                "url": "https://addons.thunderbird.net/thunderbird/downloads/file/1017958/phoenity_icons-3.0b8-tb.xpi?src=",
                "permissions": []
            }
        ],
        "is_strict_compatibility_enabled": false,
        "license": {
            "id": 3338,
            "name": {
                "en-US": "Mozilla Public License, version 2.0"
            },
            "url": "http://www.mozilla.org/MPL/2.0/"
        },
        "release_notes": {
            "en-US": "First release for Thunderbird 78, migrated using the WindowListener API.\nRestored the icon size option in the \"Customize Toolbar\" dialogs.\nLimited support for extensions (Cardbook, uBlockOrigin, Mail Redirect).\nIcon size is not always persistent (Cardbook)."
        },
        "reviewed": null,
        "url": "https://addons.thunderbird.net/en-US/thunderbird/addon/phoenity-icons/versions/3.0b8",
        "version": "3.0b8"
    },
    "default_locale": "en-US",
    "description": {
        "en-US": "This is a (limited) replacement for the <a rel=\"nofollow\" href=\"https://addons.thunderbird.net/en-US/thunderbird/addon/phoenity-shredder/\">Phoenity Shredder</a> theme.\nFull themes are no longer supported on Thunderbird 68 and higher.\n\nIcon size (small icons) can be set in the \"Customize Toolbar\" dialogs.\nSupports some extensions (Cardbook, uBlockOrigin, Mail Redirect).\n\nIcon size (small icons) is not persistent  on the Cardbook toolbar, to use small icons there you can add the following to userChrome.css:\n\n#cardbook-toolbox .toolbarbutton-1 .toolbarbutton-icon {\n  min-width: 18px !important;\n  min-height: 18px !important;\n  width: 18px !important;\n  height: 18px !important;\n}"
    },
    "developer_comments": null,
    "edit_url": "https://addons.thunderbird.net/en-US/developers/addon/phoenity-icons/edit",
    "guid": "icons@dillinger",
    "has_eula": false,
    "has_privacy_policy": false,
    "homepage": {
        "en-US": "https://addons.thunderbird.net/en-US/thunderbird/addon/phoenity-icons/"
    },
    "icon_url": "https://addons.thunderbird.net/user-media/addon_icons/986/986685-64.png?modified=dae8a351",
    "icons": {
        "32": "https://addons.thunderbird.net/user-media/addon_icons/986/986685-32.png?modified=dae8a351",
        "64": "https://addons.thunderbird.net/user-media/addon_icons/986/986685-64.png?modified=dae8a351"
    },
    "is_disabled": false,
    "is_experimental": false,
    "is_featured": false,
    "is_source_public": true,
    "last_updated": "2020-11-23T10:48:02Z",
    "name": {
        "en-US": "Phoenity Icons"
    },
    "previews": [
        {
            "id": 205700,
            "caption": {
                "en-US": "Thunderbird 70, with Phoenity Icons & Phoenity Buttons"
            },
            "image_size": [
                990,
                660
            ],
            "image_url": "https://addons.thunderbird.net/user-media/previews/full/205/205700.png?modified=1601964313",
            "thumbnail_size": [
                300,
                200
            ],
            "thumbnail_url": "https://addons.thunderbird.net/user-media/previews/thumbs/205/205700.png?modified=1601964313"
        },
        {
            "id": 206170,
            "caption": {
                "en-US": "Thunderbird 78, with Phoenity Icons & Phoenity Buttons"
            },
            "image_size": [
                990,
                660
            ],
            "image_url": "https://addons.thunderbird.net/user-media/previews/full/206/206170.png?modified=1601964318",
            "thumbnail_size": [
                300,
                200
            ],
            "thumbnail_url": "https://addons.thunderbird.net/user-media/previews/thumbs/206/206170.png?modified=1601964318"
        }
    ],
    "public_stats": true,
    "ratings": {
        "bayesian_average": 4.79268,
        "count": 36,
        "average": 4.8333,
        "text_count": 36
    },
    "ratings_url": "https://addons.thunderbird.net/en-US/thunderbird/addon/phoenity-icons/reviews/",
    "requires_payment": false,
    "review_url": "https://addons.thunderbird.net/en-US/reviewers/review/986685",
    "slug": "phoenity-icons",
    "status": "public",
    "summary": {
        "en-US": "Phoenity icons for Thunderbird"
    },
    "support_email": {
        "en-US": "dillinger@kpnmail.nl"
    },
    "support_url": null,
    "tags": [
        "firefox57"
    ],
    "type": "extension",
    "url": "https://addons.thunderbird.net/en-US/thunderbird/addon/phoenity-icons/",
    "weekly_downloads": 0,
    "xpilib": {
        "ext_comp": {
            "compNoMax": true,
            "mext": true,
            "comp68": true,
            "comp78plus": true,
            "comp78pv": true,
            "comp78pv_date": "2020-08-31T19:05:33Z",
            "comp78pv_version": "3.0b1",
            "comp78pv_vmin": "78.0",
            "comp78pv_vmax": "*"
        }
    }
}