[
    {
        "id": 2122183,
        "channel": "listed",
        "compatibility": {
            "thunderbird": {
                "max": "38.*",
                "min": "1.5"
            }
        },
        "edit_url": "https://addons.thunderbird.net/en-US/developers/addon/cix-forums/versions/2122183",
        "files": [
            {
                "id": 668495,
                "created": "2017-06-20T15:18:42Z",
                "hash": "sha256:e1824eb7872705d158a53561e848c6b753e8896ec10b403f9b0ee7ba3849a4ce",
                "is_restart_required": true,
                "is_webextension": false,
                "is_mozilla_signed_extension": false,
                "platform": "all",
                "size": 5158,
                "status": "public",
                "url": "https://addons.thunderbird.net/thunderbird/downloads/file/668495/cix_forums-1.2-tb.xpi?src=",
                "permissions": []
            }
        ],
        "is_strict_compatibility_enabled": true,
        "license": {
            "id": 3653,
            "name": {
                "en-US": "CIX Online Licence"
            },
            "text": {
                "en-US": "Copyright CIX Online Ltd, All Rights Reserved."
            },
            "url": "https://addons.thunderbird.net/en-US/thunderbird/addon/cix-forums/license/1.2"
        },
        "release_notes": {
            "en-US": "Updated the URL for accessing CIX Forums.\nSign up for a free CIX account at <a rel=\"nofollow\" href=\"https://outgoing.prod.mozaws.net/v1/1b029ea73c0298821edcc8bd372d1e391de4a3daee15cee7c5cf930beb6f09f0/http%3A//forums.cix.co.uk/signUp.aspx%3Fp=cixbasic\">http://forums.cix.co.uk/signUp.aspx?p=cixbasic</a>. This takes seconds and only asks for your email address, to choose a nickname and a password. There is a activation email so the email address needs to be real."
        },
        "reviewed": null,
        "url": "https://addons.thunderbird.net/en-US/thunderbird/addon/cix-forums/versions/1.2",
        "version": "1.2"
    },
    {
        "id": 1484126,
        "channel": "listed",
        "compatibility": {
            "thunderbird": {
                "max": "17.*",
                "min": "1.5"
            }
        },
        "edit_url": "https://addons.thunderbird.net/en-US/developers/addon/cix-forums/versions/1484126",
        "files": [
            {
                "id": 225631,
                "created": "2013-08-22T05:14:29Z",
                "hash": "sha256:178c089b549779e76065f60cf2167ebbbfd9b547b88c4d94e75c16796b8845c4",
                "is_restart_required": true,
                "is_webextension": false,
                "is_mozilla_signed_extension": false,
                "platform": "all",
                "size": 5163,
                "status": "public",
                "url": "https://addons.thunderbird.net/thunderbird/downloads/file/225631/cix_forums-1.1-tb.xpi?src=",
                "permissions": []
            }
        ],
        "is_strict_compatibility_enabled": true,
        "license": {
            "id": 3653,
            "name": {
                "en-US": "CIX Online Licence"
            },
            "text": {
                "en-US": "Copyright CIX Online Ltd, All Rights Reserved."
            },
            "url": "https://addons.thunderbird.net/en-US/thunderbird/addon/cix-forums/license/1.1"
        },
        "release_notes": {
            "en-US": "Changed to use SSL URL\nChanged the on hover title so that it fits properly with icons and text displayed."
        },
        "reviewed": null,
        "url": "https://addons.thunderbird.net/en-US/thunderbird/addon/cix-forums/versions/1.1",
        "version": "1.1"
    },
    {
        "id": 1481039,
        "channel": "listed",
        "compatibility": {
            "thunderbird": {
                "max": "17.*",
                "min": "1.5"
            }
        },
        "edit_url": "https://addons.thunderbird.net/en-US/developers/addon/cix-forums/versions/1481039",
        "files": [
            {
                "id": 224111,
                "created": "2013-08-06T06:06:25Z",
                "hash": "sha256:068823fecb19f8f17cf8cd31801541b1616544ca9008380fc7e901f63178a0c8",
                "is_restart_required": true,
                "is_webextension": false,
                "is_mozilla_signed_extension": false,
                "platform": "all",
                "size": 5133,
                "status": "public",
                "url": "https://addons.thunderbird.net/thunderbird/downloads/file/224111/cix_forums-1.0-tb.xpi?src=",
                "permissions": []
            }
        ],
        "is_strict_compatibility_enabled": true,
        "license": {
            "id": 3653,
            "name": {
                "en-US": "CIX Online Licence"
            },
            "text": {
                "en-US": "Copyright CIX Online Ltd, All Rights Reserved."
            },
            "url": "https://addons.thunderbird.net/en-US/thunderbird/addon/cix-forums/license/1.0"
        },
        "release_notes": null,
        "reviewed": "2013-08-18T08:18:38Z",
        "url": "https://addons.thunderbird.net/en-US/thunderbird/addon/cix-forums/versions/1.0",
        "version": "1.0"
    }
]